[
  {
    "Id": 1,
    "title": "Deliver Address",
    "street1": "Street1",
    "street2": "Street2",
    "street3": "Street3",
    "county": "Import",
    "postCode": "Customer",
    "country": "United Kingdom",
    "isPrimary": false
  },
  {
    "Id": 2,
    "title": "Primary Address",
    "street1": "Street1",
    "street2": "Street2",
    "street3": "Street3",
    "county": "Import",
    "postCode": "Customer",
    "country": "United Kingdom",
    "isPrimary": true
  },
  {
    "Id": 5,
    "title": "Collection Address",
    "street1": "Street1",
    "street2": "Street2",
    "street3": "Street3",
    "county": "Import",
    "postCode": "Customer",
    "country": "United Kingdom",
    "isPrimary": false
  },
  {
    "Id": 8,
    "title": "Invoice Address",
    "street1": "Street1",
    "street2": "Street2",
    "street3": "Street3",
    "county": "Import",
    "postCode": "Customer",
    "country": "United Kingdom",
    "isPrimary": false
  },
  {
    "Id": 10,
    "title": "Deliver Address",
    "street1": "Street1",
    "street2": "Street2",
    "street3": "Street3",
    "county": "Import",
    "postCode": "Customer",
    "country": "United Kingdom",
    "isPrimary": false
  }
]
